gcsv/__init__.py
gcsv/gcsv.py
gcsv-0.1.0.dist-info/LICENSE
gcsv-0.1.0.dist-info/WHEEL
gcsv-0.1.0.dist-info/METADATA
gcsv-0.1.0.dist-info/RECORD
